ita_toolkit/extraction.py
ita_toolkit/cleanse/cleanse.py
ita_toolkit/load/load.py
ita_toolkit/transform/transform.py
ita_toolkit-0.1.3.dist-info/METADATA
ita_toolkit-0.1.3.dist-info/WHEEL
ita_toolkit-0.1.3.dist-info/top_level.txt
ita_toolkit-0.1.3.dist-info/RECORD
