Metadata-Version: 2.4
Name: ita-toolkit
Version: 0.1.3
Summary: Add your description here
Requires-Python: >=3.12
Requires-Dist: azure-identity>=1.24.0
Requires-Dist: dotenv>=0.9.9
Requires-Dist: pyodbc>=5.2.0
